eevb/__main__.py
eevb/core.py
eevb/globals.py
eevb/main.py
eevb/models.py
eevb/data/enigmavbconsole.exe
eevb-0.2.2.dist-info/METADATA
eevb-0.2.2.dist-info/WHEEL
eevb-0.2.2.dist-info/entry_points.txt
eevb-0.2.2.dist-info/top_level.txt
eevb-0.2.2.dist-info/RECORD
