Metadata-Version: 2.4
Name: eevb
Version: 0.2.2
Summary: EEVB simplifies Enigma Virtual Box command-line usage by building virtualized executables via a JSON configuration file.
Requires-Python: >=3.12
Requires-Dist: pydantic>=2.11.7
